tan_utils/__init__.py
tan_utils/tan_utils_cli.py
tan_utils-0.0.3.dist-info/METADATA
tan_utils-0.0.3.dist-info/RECORD
tan_utils-0.0.3.dist-info/WHEEL
tan_utils-0.0.3.dist-info/entry_points.txt
tan_utils-0.0.3.dist-info/top_level.txt
