Metadata-Version: 2.1
Name: tan-utils
Version: 0.0.3
Summary: Tan's utilities
Home-page: https://github.com/tannn1995/tan_utils
Author: Tan Nguyen
Author-email: tan.nguyen.tn@hotmail.com
License: UNKNOWN
Platform: UNKNOWN
Classifier: Programming Language :: Python :: 3
Classifier: License :: OSI Approved :: MIT License
Classifier: Operating System :: OS Independent
